[
  {
    "id": "act-001",
    "type": "Call",
    "subject": "Discovery call with Sarah Chen",
    "notes": "Discussed their current CRM pain points and requirements. Very interested in our enterprise solution.",
    "relatedTo": "Sarah Chen",
    "relatedType": "Contact",
    "relatedId": "c1",
    "dueDate": "2026-01-26",
    "completedDate": null,
    "status": "Pending",
    "assignedTo": "John Smith",
    "createdAt": "2026-01-24"
  },
  {
    "id": "act-002",
    "type": "Email",
    "subject": "Send proposal to Acme Corporation",
    "notes": "Include pricing for enterprise tier and implementation timeline.",
    "relatedTo": "Acme Corporation",
    "relatedType": "Company",
    "relatedId": "comp-001",
    "dueDate": "2026-01-25",
    "completedDate": "2026-01-25",
    "status": "Completed",
    "assignedTo": "John Smith",
    "createdAt": "2026-01-23"
  },
  {
    "id": "act-003",
    "type": "Meeting",
    "subject": "Product demo with TechStart Inc",
    "notes": "Demo the cloud migration features. Marcus will join with his team.",
    "relatedTo": "Cloud Migration Project",
    "relatedType": "Deal",
    "relatedId": "deal-002",
    "dueDate": "2026-01-27",
    "completedDate": null,
    "status": "Pending",
    "assignedTo": "Sarah Johnson",
    "createdAt": "2026-01-22"
  },
  {
    "id": "act-004",
    "type": "Task",
    "subject": "Prepare contract for Annual Support renewal",
    "notes": "Standard terms, 10% discount for early renewal.",
    "relatedTo": "Annual Support Contract",
    "relatedType": "Deal",
    "relatedId": "deal-003",
    "dueDate": "2026-01-20",
    "completedDate": "2026-01-19",
    "status": "Completed",
    "assignedTo": "Emily Davis",
    "createdAt": "2026-01-15"
  },
  {
    "id": "act-005",
    "type": "Call",
    "subject": "Follow-up call with Marcus Johnson",
    "notes": "Discuss next steps after the proposal review.",
    "relatedTo": "Marcus Johnson",
    "relatedType": "Contact",
    "relatedId": "c2",
    "dueDate": "2026-01-22",
    "completedDate": null,
    "status": "Overdue",
    "assignedTo": "John Smith",
    "createdAt": "2026-01-18"
  },
  {
    "id": "act-006",
    "type": "Email",
    "subject": "Send case studies to Global Finance",
    "notes": "They requested financial services industry case studies.",
    "relatedTo": "Global Finance Partners",
    "relatedType": "Company",
    "relatedId": "comp-003",
    "dueDate": "2026-01-26",
    "completedDate": null,
    "status": "Pending",
    "assignedTo": "Sarah Johnson",
    "createdAt": "2026-01-24"
  },
  {
    "id": "act-007",
    "type": "Meeting",
    "subject": "Quarterly business review with HealthFirst",
    "notes": "Review Q4 results and discuss Q1 expansion plans.",
    "relatedTo": "HealthFirst Medical",
    "relatedType": "Company",
    "relatedId": "comp-004",
    "dueDate": "2026-01-28",
    "completedDate": null,
    "status": "Pending",
    "assignedTo": "Emily Davis",
    "createdAt": "2026-01-20"
  },
  {
    "id": "act-008",
    "type": "Task",
    "subject": "Update CRM with meeting notes",
    "notes": "Add notes from all client meetings this week.",
    "relatedTo": "Emily Rodriguez",
    "relatedType": "Contact",
    "relatedId": "c3",
    "dueDate": "2026-01-24",
    "completedDate": "2026-01-24",
    "status": "Completed",
    "assignedTo": "John Smith",
    "createdAt": "2026-01-22"
  },
  {
    "id": "act-009",
    "type": "Call",
    "subject": "Check in with James Williams",
    "notes": "See if they have budget approval for Q1.",
    "relatedTo": "James Williams",
    "relatedType": "Contact",
    "relatedId": "c4",
    "dueDate": "2026-01-15",
    "completedDate": null,
    "status": "Overdue",
    "assignedTo": "Sarah Johnson",
    "createdAt": "2026-01-10"
  },
  {
    "id": "act-010",
    "type": "Email",
    "subject": "Send integration documentation",
    "notes": "Technical docs for API integration with their existing systems.",
    "relatedTo": "Data Analytics Platform",
    "relatedType": "Deal",
    "relatedId": "deal-005",
    "dueDate": "2026-01-27",
    "completedDate": null,
    "status": "Pending",
    "assignedTo": "Emily Davis",
    "createdAt": "2026-01-25"
  },
  {
    "id": "act-011",
    "type": "Meeting",
    "subject": "Contract negotiation with PeopleFirst HR",
    "notes": "Final terms discussion. Legal team will join.",
    "relatedTo": "HR Management System",
    "relatedType": "Deal",
    "relatedId": "deal-007",
    "dueDate": "2026-01-26",
    "completedDate": null,
    "status": "Pending",
    "assignedTo": "John Smith",
    "createdAt": "2026-01-21"
  },
  {
    "id": "act-012",
    "type": "Task",
    "subject": "Review security audit requirements",
    "notes": "Prepare documentation for compliance review.",
    "relatedTo": "Precision Manufacturing Inc",
    "relatedType": "Company",
    "relatedId": "comp-006",
    "dueDate": "2026-01-23",
    "completedDate": "2026-01-23",
    "status": "Completed",
    "assignedTo": "Sarah Johnson",
    "createdAt": "2026-01-19"
  },
  {
    "id": "act-013",
    "type": "Call",
    "subject": "Introduction call with Retail Solutions",
    "notes": "New lead from trade show. Interested in inventory management.",
    "relatedTo": "Retail Solutions Group",
    "relatedType": "Company",
    "relatedId": "comp-007",
    "dueDate": "2026-01-25",
    "completedDate": "2026-01-25",
    "status": "Completed",
    "assignedTo": "Emily Davis",
    "createdAt": "2026-01-23"
  },
  {
    "id": "act-014",
    "type": "Email",
    "subject": "Send onboarding materials to EduTech",
    "notes": "Welcome package and getting started guide.",
    "relatedTo": "EduTech Learning",
    "relatedType": "Company",
    "relatedId": "comp-008",
    "dueDate": "2026-01-21",
    "completedDate": "2026-01-21",
    "status": "Completed",
    "assignedTo": "John Smith",
    "createdAt": "2026-01-20"
  },
  {
    "id": "act-015",
    "type": "Meeting",
    "subject": "Technical requirements workshop",
    "notes": "Gather detailed requirements for custom integration.",
    "relatedTo": "Mobile App Development",
    "relatedType": "Deal",
    "relatedId": "deal-009",
    "dueDate": "2026-01-29",
    "completedDate": null,
    "status": "Pending",
    "assignedTo": "Sarah Johnson",
    "createdAt": "2026-01-24"
  },
  {
    "id": "act-016",
    "type": "Task",
    "subject": "Create ROI analysis for Logistics Express",
    "notes": "Calculate potential savings from automation.",
    "relatedTo": "Logistics Express",
    "relatedType": "Company",
    "relatedId": "comp-010",
    "dueDate": "2026-01-18",
    "completedDate": null,
    "status": "Overdue",
    "assignedTo": "Emily Davis",
    "createdAt": "2026-01-14"
  },
  {
    "id": "act-017",
    "type": "Call",
    "subject": "Status check with Aisha Patel",
    "notes": "Monthly check-in call to discuss any issues.",
    "relatedTo": "Aisha Patel",
    "relatedType": "Contact",
    "relatedId": "c5",
    "dueDate": "2026-01-26",
    "completedDate": null,
    "status": "Pending",
    "assignedTo": "John Smith",
    "createdAt": "2026-01-23"
  },
  {
    "id": "act-018",
    "type": "Email",
    "subject": "Follow up on proposal feedback",
    "notes": "Check if they have any questions about pricing.",
    "relatedTo": "Inventory Management System",
    "relatedType": "Deal",
    "relatedId": "deal-012",
    "dueDate": "2026-01-24",
    "completedDate": "2026-01-24",
    "status": "Completed",
    "assignedTo": "Sarah Johnson",
    "createdAt": "2026-01-22"
  },
  {
    "id": "act-019",
    "type": "Meeting",
    "subject": "Stakeholder alignment meeting",
    "notes": "Get all decision makers in one room to finalize scope.",
    "relatedTo": "Compliance Management Suite",
    "relatedType": "Deal",
    "relatedId": "deal-017",
    "dueDate": "2026-01-30",
    "completedDate": null,
    "status": "Pending",
    "assignedTo": "Emily Davis",
    "createdAt": "2026-01-25"
  },
  {
    "id": "act-020",
    "type": "Task",
    "subject": "Update pipeline forecast",
    "notes": "Review all deals and update probability estimates.",
    "relatedTo": "Robert Kim",
    "relatedType": "Contact",
    "relatedId": "c6",
    "dueDate": "2026-01-25",
    "completedDate": "2026-01-25",
    "status": "Completed",
    "assignedTo": "John Smith",
    "createdAt": "2026-01-23"
  },
  {
    "id": "act-021",
    "type": "Call",
    "subject": "Reference check discussion",
    "notes": "Connect prospect with existing customer for reference.",
    "relatedTo": "Lisa Thompson",
    "relatedType": "Contact",
    "relatedId": "c7",
    "dueDate": "2026-01-27",
    "completedDate": null,
    "status": "Pending",
    "assignedTo": "Sarah Johnson",
    "createdAt": "2026-01-24"
  },
  {
    "id": "act-022",
    "type": "Email",
    "subject": "Send renewal reminder",
    "notes": "Contract expires in 30 days. Start renewal discussion.",
    "relatedTo": "Creative Media Agency",
    "relatedType": "Company",
    "relatedId": "comp-011",
    "dueDate": "2026-01-19",
    "completedDate": null,
    "status": "Overdue",
    "assignedTo": "Emily Davis",
    "createdAt": "2026-01-15"
  },
  {
    "id": "act-023",
    "type": "Meeting",
    "subject": "Training session for new features",
    "notes": "Walk through the new dashboard and reporting features.",
    "relatedTo": "Jennifer Lee",
    "relatedType": "Contact",
    "relatedId": "c9",
    "dueDate": "2026-01-28",
    "completedDate": null,
    "status": "Pending",
    "assignedTo": "John Smith",
    "createdAt": "2026-01-25"
  },
  {
    "id": "act-024",
    "type": "Task",
    "subject": "Prepare demo environment",
    "notes": "Set up sandbox with sample data for prospect demo.",
    "relatedTo": "Financial Reporting Tool",
    "relatedType": "Deal",
    "relatedId": "deal-016",
    "dueDate": "2026-01-26",
    "completedDate": null,
    "status": "Pending",
    "assignedTo": "Sarah Johnson",
    "createdAt": "2026-01-24"
  },
  {
    "id": "act-025",
    "type": "Call",
    "subject": "Win-back call with David Martinez",
    "notes": "Check if they are ready to re-engage after budget freeze ended.",
    "relatedTo": "David Martinez",
    "relatedType": "Contact",
    "relatedId": "c8",
    "dueDate": "2026-01-26",
    "completedDate": null,
    "status": "Pending",
    "assignedTo": "Emily Davis",
    "createdAt": "2026-01-24"
  }
]
